[
  {
    "package": "mynotebooks",
    "url": "https://github.com/Aariq/mynotebooks"
  },
  {
    "package": "chemhelper",
    "url": "https://github.com/Aariq/chemhelper"
  },
  {
    "package": "bdffpRain",
    "url": "https://github.com/BrunaLab/bdffpRain"
  },
  {
    "package": "webchem",
    "url": "https://github.com/ropensci/webchem"
  },
  {
    "package": "holodeck",
    "url": "https://github.com/Aariq/holodeck"
  },
  {
    "package": "pkg1",
    "url": "https://github.com/Aariq/monorepo/tree/main/pkg1"
  },
  {
    "package": "pkg2",
    "url": "https://github.com/Aariq/monorepo/tree/main/pkg2"
  },
  {
    "package": "monorepo",
    "url": "https://github.com/Aariq/monorepo"
  }
]
